{"lagrange.core_login_loginbyscanqrcode.md":"BWyBGKnG","lagrange.core_createbot_index.md":"Bm3gtKAq","lagrange.core_login_loginbypassword.md":"Djs0Avyv","lagrange.core_send_index.md":"Dz8w1BFN","lagrange.core_messageentity_textentity.md":"CAWFLj3l","lagrange.core_messageentity_fileentity.md":"CRfnNW88","lagrange.core_login_index.md":"CXuiNYO8","lagrange.core_index.md":"CrKiCWrM","index.md":"C2FJuyJV","lagrange.core_messageentity_forwardentity.md":"DIAnwhtS","lagrange.core_event_eventinvoker.md":"eQPF3w4U","lagrange.core_messageentity_imessageentity.md":"DOpVnMgB","lagrange.core_login_extern.md":"BuU2a9EK","lagrange.core_messagechain_messagebuilder.md":"D5NWaCrw","lagrange.onebot_api_extend_index.md":"DBgI7Qjd","lagrange.core_messageentity_multimsgentity.md":"B6Dx4GGO","lagrange.core_messageentity_index.md":"DWXfVNeA","lagrange.core_send_sendmessage.md":"CK5cWZn5","lagrange.onebot_index.md":"CxH8KKMy","lagrange.core_messageentity_jsonentity.md":"CSmqUjJv","lagrange.core_messageentity_videoentity.md":"rbn-sprW","lagrange.core_event_eventargs.md":"BYDujt6D","lagrange.onebot_segment_extend_index.md":"Ba8FIoTX","lagrange.core_send_messageresult.md":"C8L-rSEF","lagrange.core_messagechain_index.md":"BxelcxfA","lagrange.onebot_api_onebot_index.md":"CUOJmIUg","lagrange.core_messageentity_faceentity.md":"BuomFk_0","lagrange.onebot_config_index.md":"_NsKwdnW","lagrange.core_messagechain_parsemessagechain.md":"EBwT7f-M","lagrange.core_messageentity_xmlentity.md":"CfshRJrW","lagrange.core_messageentity_mentionentity.md":"DrGaU8QT","lagrange.core_messagechain_messagechain.md":"DM-YjXuX","lagrange.onebot_segment_onebot_index.md":"BlK03xWp","lagrange.core_event_index.md":"ChnNbbbz","lagrange.core_messageentity_imageentity.md":"qdEyUGf-"}
